cytra/__init__.py
cytra/application.py
cytra/constants.py
cytra/cors.py
cytra/exceptions.py
cytra/helpers.py
cytra/i18n.py
cytra/json.py
cytra/log.py
cytra/redis.py
cytra/template.py
cytra/testing.py
cytra/auth/__init__.py
cytra/auth/app_mixin.py
cytra/auth/authenticator.py
cytra/auth/principal.py
cytra/auth/stateful_authenticator.py
cytra/db/__init__.py
cytra/db/access_control_mixin.py
cytra/db/activation_mixin.py
cytra/db/app_mixin.py
cytra/db/attrstate_mixin.py
cytra/db/base.py
cytra/db/created_mixin.py
cytra/db/field.py
cytra/db/filtering_mixin.py
cytra/db/inspection_mixin.py
cytra/db/manager.py
cytra/db/modified_mixin.py
cytra/db/ordering_mixin.py
cytra/db/pagination_mixin.py
cytra/db/serialize_mixin.py
cytra/db/transform_mixin.py
cytra-0.18.1.dist-info/METADATA
cytra-0.18.1.dist-info/WHEEL
cytra-0.18.1.dist-info/top_level.txt
cytra-0.18.1.dist-info/RECORD
