Metadata-Version: 2.1
Name: cytra
Version: 0.18.1
Summary: UNKNOWN
Home-page: UNKNOWN
License: UNKNOWN
Keywords: database
Platform: UNKNOWN
Requires-Dist: gongish (>=0.11.0)
Requires-Dist: sqlalchemy (>=1.4.0)
Requires-Dist: pytz (>=2021.1)
Requires-Dist: PyJWT (>=2.1.0)
Requires-Dist: redis (>=3.5.3)
Requires-Dist: user-agents (>=2.2.0)
Requires-Dist: webtest (>=2.0.35)
Provides-Extra: ujson
Requires-Dist: ujson (>=4.0.0) ; extra == 'ujson'
